api_to_dataframe/__init__.py
api_to_dataframe/controller/client_builder.py
api_to_dataframe/models/get_data.py
api_to_dataframe/models/retainer.py
api_to_dataframe/utils/__init__.py
api_to_dataframe/utils/logger.py
api_to_dataframe-2.0.4.dist-info/LICENSE
api_to_dataframe-2.0.4.dist-info/METADATA
api_to_dataframe-2.0.4.dist-info/WHEEL
api_to_dataframe-2.0.4.dist-info/RECORD
