Metadata-Version: 2.1
Name: api-to-dataframe
Version: 2.0.4
Summary: A package to convert API responses to pandas dataframe
License: MIT
Author: IvanildoBarauna
Author-email: ivanildo.jnr@outlook.com
Requires-Python: >=3.9,<4.0
Classifier: Development Status :: 5 - Production/Stable
Classifier: Intended Audience :: Developers
Classifier: License :: OSI Approved :: MIT License
Classifier: Programming Language :: Python :: 3
Classifier: Programming Language :: Python :: 3.9
Classifier: Programming Language :: Python :: 3.10
Classifier: Programming Language :: Python :: 3.11
Classifier: Programming Language :: Python :: 3.8
Requires-Dist: logging (>=0.4.9.6,<0.5.0.0)
Requires-Dist: pandas (>=2.2.3,<3.0.0)
Requires-Dist: requests (>=2.32.3,<3.0.0)
Project-URL: Documentation, https://github.com/IvanildoBarauna/api-to-dataframe/blob/main/README.md
Project-URL: Homepage, https://pypi.org/project/api-to-dataframe
Project-URL: ImplementationCase, https://github.com/IvanildoBarauna/ETL-awesome-api
Project-URL: Issues, https://github.com/IvanildoBarauna/api-to-dataframe/issues
Project-URL: Notebook, https://github.com/IvanildoBarauna/api-to-dataframe/blob/main/notebooks/example.ipynb
Project-URL: Repository, https://github.com/IvanildoBarauna/api-to-dataframe
